sukta/__init__.py
sukta/logging.py
sukta/nn/__init__.py
sukta/nn/checkpoint.py
sukta/nn/stream_norm.py
sukta/nn/utils.py
sukta/plot/__init__.py
sukta/plot/colors.py
sukta/plot/configs.py
sukta/plot/styles/__init__.py
sukta/plot/styles/default.mplstyle
sukta/plot/utils.py
sukta/py.typed
sukta/runner.py
sukta/sem/README.md
sukta/sem/__init__.py
sukta/sem/manager.py
sukta/sem/re_patterns.py
sukta/sem/str_to_type.py
sukta/sem/structure_parsing.py
sukta/telemetry.py
sukta/utils/__init__.py
sukta/utils/tree.py
sukta-0.0.19.dist-info/WHEEL
sukta-0.0.19.dist-info/METADATA
sukta-0.0.19.dist-info/RECORD
