Metadata-Version: 2.4
Name: sukta
Version: 0.0.19
Summary: Personalized CLU and experiment tracking utility
Author: Arjun Krishna
Author-email: Arjun Krishna <arjunkris96@gmail.com>
License-Expression: BSD-3-Clause
Requires-Dist: aim>=3.29.1
Requires-Dist: cloudpickle>=3.1.1
Requires-Dist: dacite>=1.9.2
Requires-Dist: jsonargparse>=4.41.0
Requires-Dist: matplotlib>=3.10.6
Requires-Dist: pandas>=2.3.3
Requires-Dist: python-benedict[yaml]>=0.35.0
Requires-Dist: rich>=14.1.0
Requires-Dist: adjusttext>=1.3.0
Requires-Dist: bumpver ; extra == 'dev'
Requires-Dist: build ; extra == 'dev'
Requires-Dist: ruff ; extra == 'dev'
Requires-Dist: twine ; extra == 'dev'
Requires-Dist: pre-commit ; extra == 'dev'
Requires-Dist: pytest ; extra == 'dev'
Requires-Dist: jax>=0.6 ; extra == 'jax'
Requires-Dist: jaxtyping>=0.3.3 ; extra == 'jax'
Requires-Dist: equinox>=0.13.1 ; extra == 'jax'
Requires-Dist: orbax-checkpoint>=0.11.25 ; extra == 'jax'
Requires-Python: >=3.10
Provides-Extra: dev
Provides-Extra: jax
